{
	"configurations" : 
	[
		{
			"directories" : 
			[
				{
					"build" : ".",
					"childIndexes" : 
					[
						1,
						4,
						5
					],
					"hasInstallRule" : true,
					"jsonFile" : "directory-.-Debug-f5ebdc15457944623624.json",
					"minimumCMakeVersion" : 
					{
						"string" : "3.14"
					},
					"projectIndex" : 0,
					"source" : "."
				},
				{
					"build" : "_deps/googletest-build",
					"childIndexes" : 
					[
						2
					],
					"hasInstallRule" : true,
					"jsonFile" : "directory-_deps.googletest-build-Debug-fa1b18db30f420365ea4.json",
					"minimumCMakeVersion" : 
					{
						"string" : "2.8.12"
					},
					"parentIndex" : 0,
					"projectIndex" : 1,
					"source" : "cmake-build-debug/_deps/googletest-src"
				},
				{
					"build" : "_deps/googletest-build/googlemock",
					"childIndexes" : 
					[
						3
					],
					"hasInstallRule" : true,
					"jsonFile" : "directory-_deps.googletest-build.googlemock-Debug-71768b19b442d0f5e441.json",
					"minimumCMakeVersion" : 
					{
						"string" : "2.8.12"
					},
					"parentIndex" : 1,
					"projectIndex" : 2,
					"source" : "cmake-build-debug/_deps/googletest-src/googlemock",
					"targetIndexes" : 
					[
						2,
						3
					]
				},
				{
					"build" : "_deps/googletest-build/googletest",
					"hasInstallRule" : true,
					"jsonFile" : "directory-_deps.googletest-build.googletest-Debug-6e084a9772ec68cf639c.json",
					"minimumCMakeVersion" : 
					{
						"string" : "2.8.12"
					},
					"parentIndex" : 2,
					"projectIndex" : 3,
					"source" : "cmake-build-debug/_deps/googletest-src/googletest",
					"targetIndexes" : 
					[
						4,
						5
					]
				},
				{
					"build" : "src",
					"jsonFile" : "directory-src-Debug-b6cf2213fc5053b67c22.json",
					"minimumCMakeVersion" : 
					{
						"string" : "3.14"
					},
					"parentIndex" : 0,
					"projectIndex" : 0,
					"source" : "src",
					"targetIndexes" : 
					[
						0
					]
				},
				{
					"build" : "test",
					"jsonFile" : "directory-test-Debug-451c0598f41488bb20b9.json",
					"minimumCMakeVersion" : 
					{
						"string" : "3.14"
					},
					"parentIndex" : 0,
					"projectIndex" : 0,
					"source" : "test",
					"targetIndexes" : 
					[
						1
					]
				}
			],
			"name" : "Debug",
			"projects" : 
			[
				{
					"childIndexes" : 
					[
						1
					],
					"directoryIndexes" : 
					[
						0,
						4,
						5
					],
					"name" : "playground",
					"targetIndexes" : 
					[
						0,
						1
					]
				},
				{
					"childIndexes" : 
					[
						2
					],
					"directoryIndexes" : 
					[
						1
					],
					"name" : "googletest-distribution",
					"parentIndex" : 0
				},
				{
					"childIndexes" : 
					[
						3
					],
					"directoryIndexes" : 
					[
						2
					],
					"name" : "gmock",
					"parentIndex" : 1,
					"targetIndexes" : 
					[
						2,
						3
					]
				},
				{
					"directoryIndexes" : 
					[
						3
					],
					"name" : "gtest",
					"parentIndex" : 2,
					"targetIndexes" : 
					[
						4,
						5
					]
				}
			],
			"targets" : 
			[
				{
					"directoryIndex" : 4,
					"id" : "PgLib::@145eef247bfb46b6828c",
					"jsonFile" : "target-PgLib-Debug-8f288d8610eed7c3bf38.json",
					"name" : "PgLib",
					"projectIndex" : 0
				},
				{
					"directoryIndex" : 5,
					"id" : "TestVisitor::@36f028580bb02cc8272a",
					"jsonFile" : "target-TestVisitor-Debug-0608466b56126e99452a.json",
					"name" : "TestVisitor",
					"projectIndex" : 0
				},
				{
					"directoryIndex" : 2,
					"id" : "gmock::@0f7bb11d64f3678238c7",
					"jsonFile" : "target-gmock-Debug-6ab8748b0c85aca36dfc.json",
					"name" : "gmock",
					"projectIndex" : 2
				},
				{
					"directoryIndex" : 2,
					"id" : "gmock_main::@0f7bb11d64f3678238c7",
					"jsonFile" : "target-gmock_main-Debug-a32a79e4165510930678.json",
					"name" : "gmock_main",
					"projectIndex" : 2
				},
				{
					"directoryIndex" : 3,
					"id" : "gtest::@1ea2dfc0605fe3ab2a3f",
					"jsonFile" : "target-gtest-Debug-170917f455eb2b5a71b4.json",
					"name" : "gtest",
					"projectIndex" : 3
				},
				{
					"directoryIndex" : 3,
					"id" : "gtest_main::@1ea2dfc0605fe3ab2a3f",
					"jsonFile" : "target-gtest_main-Debug-4d51e1e0e758cc4be6e3.json",
					"name" : "gtest_main",
					"projectIndex" : 3
				}
			]
		}
	],
	"kind" : "codemodel",
	"paths" : 
	{
		"build" : "/Users/zhang/PG-VisitorPattern/cmake-build-debug",
		"source" : "/Users/zhang/PG-VisitorPattern"
	},
	"version" : 
	{
		"major" : 2,
		"minor" : 3
	}
}
